[
    {
        "id": 1,
        "category": "Wedding Dresses",
        "name": "Elegant Lace Wedding Gown",
        "img": "https://images.squarespace-cdn.com/content/v1/5a71fe7a6f4ca33202272999/1589411226047-9K88E5DWTXY8BLY84RP6/N%26DJ-367.jpg?format=750w",
        "price": 1200.00,
        "detail": "A stunning lace wedding gown with a timeless and elegant design. This dress features intricate lace detailing and a flowing train."
    },
    {
        "id": 2,
        "category": "Wedding Dresses",
        "name": "Vintage-Inspired Bridal Dress",
        "img": "https://images.squarespace-cdn.com/content/v1/5a71fe7a6f4ca33202272999/1589411226047-9K88E5DWTXY8BLY84RP6/N%26DJ-367.jpg?format=750w",
        "price": 950.00,
        "detail": "A vintage-inspired bridal dress that exudes classic charm. It's adorned with delicate embroidery and a flattering A-line silhouette."
    },
    {
        "id": 3,
        "category": "Wedding Dresses",
        "name": "Modern Minimalist Wedding Dress",
        "img": "https://images.squarespace-cdn.com/content/v1/5a71fe7a6f4ca33202272999/1589411226047-9K88E5DWTXY8BLY84RP6/N%26DJ-367.jpg?format=750w",
        "price": 1350.00,
        "detail": "For the modern bride, this minimalist wedding dress offers clean lines and a sleek silhouette. Perfect for a contemporary wedding."
    },
    {
        "id": 4,
        "category": "Wedding Rings",
        "name": "Diamond Solitaire Engagement Ring",
        "img": "https://images.squarespace-cdn.com/content/v1/5a71fe7a6f4ca33202272999/1589411226047-9K88E5DWTXY8BLY84RP6/N%26DJ-367.jpg?format=750w",
        "price": 2500.00,
        "detail": "A timeless diamond solitaire engagement ring with a brilliant-cut diamond set in a classic white gold band."
    },
    {
        "id": 5,
        "category": "Wedding Rings",
        "name": "Matching Wedding Band Set",
        "img": "https://images.squarespace-cdn.com/content/v1/5a71fe7a6f4ca33202272999/1589411226047-9K88E5DWTXY8BLY84RP6/N%26DJ-367.jpg?format=750w",
        "price": 1800.00,
        "detail": "This set includes a stunning engagement ring and matching wedding band, both adorned with sparkling diamonds."
    },
    {
        "id": 6,
        "category": "Wedding Rings",
        "name": "Rose Gold Eternity Ring",
        "img": "https://images.squarespace-cdn.com/content/v1/5a71fe7a6f4ca33202272999/1589411226047-9K88E5DWTXY8BLY84RP6/N%26DJ-367.jpg?format=750w",
        "price": 1200.00,
        "detail": "An exquisite rose gold eternity ring featuring a continuous band of shimmering diamonds, symbolizing everlasting love."
    },
    {
        "id": 7,
        "category": "Wedding Invitations",
        "name": "Vintage Floral Wedding Invitations",
        "img": "https://images.squarespace-cdn.com/content/v1/5a71fe7a6f4ca33202272999/1589411226047-9K88E5DWTXY8BLY84RP6/N%26DJ-367.jpg?format=750w",
        "price": 3.50,
        "detail": "Elegant vintage floral wedding invitations featuring delicate flower illustrations and classic typography."
    },
    {
        "id": 8,
        "category": "Wedding Invitations",
        "name": "Rustic Woodland Wedding Invites",
        "img": "https://images.squarespace-cdn.com/content/v1/5a71fe7a6f4ca33202272999/1589411226047-9K88E5DWTXY8BLY84RP6/N%26DJ-367.jpg?format=750w",
        "price": 2.75,
        "detail": "Capture the charm of a woodland wedding with these rustic-inspired invitations adorned with woodland motifs."
    },
    {
        "id": 9,
        "category": "Wedding Invitations",
        "name": "Modern Geometric Wedding Cards",
        "img": "https://images.squarespace-cdn.com/content/v1/5a71fe7a6f4ca33202272999/1589411226047-9K88E5DWTXY8BLY84RP6/N%26DJ-367.jpg?format=750w",
        "price": 4.00,
        "detail": "Contemporary and stylish wedding cards with geometric designs and a touch of gold foil accents."
    },
    {
        "id": 10,
        "category": "Wedding Decorations",
        "name": "Crystal Chandelier Centerpiece",
        "img": "https://images.squarespace-cdn.com/content/v1/5a71fe7a6f4ca33202272999/1589411226047-9K88E5DWTXY8BLY84RP6/N%26DJ-367.jpg?format=750w",
        "price": 85.00,
        "detail": "Elevate your reception decor with these exquisite crystal chandelier centerpieces that add a touch of luxury."
    },
    {
        "id": 11,
        "category": "Wedding Decorations",
        "name": "Rustic Wedding Table Numbers",
        "img": "https://images.squarespace-cdn.com/content/v1/5a71fe7a6f4ca33202272999/1589411226047-9K88E5DWTXY8BLY84RP6/N%26DJ-367.jpg?format=750w",
        "price": 6.50,
        "detail": "Set the table in style with these rustic wooden table numbers, perfect for a country-themed wedding."
    },
    {
        "id": 12,
        "category": "Wedding Decorations",
        "name": "Gold Foil Confetti Balloons",
        "img": "https://images.squarespace-cdn.com/content/v1/5a71fe7a6f4ca33202272999/1589411226047-9K88E5DWTXY8BLY84RP6/N%26DJ-367.jpg?format=750w",
        "price": 12.00,
        "detail": "Add a touch of glamour to your wedding venue with these gold foil confetti balloons that sparkle and shine."
    }
]